profile_user_local/__init__.py
profile_user_local/profile_user.py
profile_user_local/profile_user_constants.py
profile_user_local-0.0.12.dist-info/METADATA
profile_user_local-0.0.12.dist-info/WHEEL
profile_user_local-0.0.12.dist-info/top_level.txt
profile_user_local-0.0.12.dist-info/RECORD
